LICENCE.md
MANIFEST.in
README.md
pyproject.toml
setup.py
fast_fisher/__init__.py
fast_fisher/fast_fisher_cython.c
fast_fisher/fast_fisher_cython.pyx
fast_fisher/fast_fisher_numba.py
fast_fisher/fast_fisher_python.py
fast_fisher.egg-info/PKG-INFO
fast_fisher.egg-info/SOURCES.txt
fast_fisher.egg-info/dependency_links.txt
fast_fisher.egg-info/top_level.txt