Metadata-Version: 2.1
Name: fast-fisher
Version: 0.0.4
Summary: Calculate Fisher's exact test very quickly.
Home-page: https://github.com/mrtomrod/fast_fisher
Author: Thomas Roder
Author-email: roder.thomas@gmail.com
License: MIT
Platform: UNKNOWN
Classifier: License :: OSI Approved :: MIT License
Classifier: Programming Language :: Python :: 3
Classifier: Programming Language :: Python :: 3.10
License-File: LICENCE.md
